README.md
setup.cfg
setup.py
NCP_ELSA/ELSA.py
NCP_ELSA/__init__.py
NCP_ELSA.egg-info/PKG-INFO
NCP_ELSA.egg-info/SOURCES.txt
NCP_ELSA.egg-info/dependency_links.txt
NCP_ELSA.egg-info/requires.txt
NCP_ELSA.egg-info/top_level.txt