Metadata-Version: 1.2
Name: NCP-ELSA
Version: 0.14
Summary: This is for ELSA(Effective Log Search & Analytics) service of NAVER Cloud Platform
Home-page: https://github.com/ultimatelife/NCP_ELSA_PYTHON
Author: geonwoo.kim
Author-email: drama0708@gmail.com
License: Naver Cloud Platform
Keywords: NCP,clova,ELSA,NCP_ELSA,elsa
Platform: UNKNOWN
Classifier: Programming Language :: Python :: 3.6
Requires-Python: >=3.6
